XStatic_JQuery_Migrate-3.3.2.1-nspkg.pth
xstatic/pkg/jquery_migrate/__init__.py
xstatic/pkg/jquery_migrate/data/jquery-migrate.js
xstatic/pkg/jquery_migrate/data/jquery-migrate.min.js
XStatic_JQuery_Migrate-3.3.2.1.dist-info/METADATA
XStatic_JQuery_Migrate-3.3.2.1.dist-info/WHEEL
XStatic_JQuery_Migrate-3.3.2.1.dist-info/namespace_packages.txt
XStatic_JQuery_Migrate-3.3.2.1.dist-info/top_level.txt
XStatic_JQuery_Migrate-3.3.2.1.dist-info/RECORD
