Metadata-Version: 2.1
Name: XStatic-JQuery-Migrate
Version: 3.3.2.1
Summary: JQuery-Migrate 3.3.2 (XStatic packaging standard)
Home-page: https://github.com/jquery/jquery-migrate
Maintainer: Radomir Dopieralski
Maintainer-email: openstack@sheep.art.pl
License: (same as JQuery-Migrate)
Keywords: jquery_migrate xstatic
Platform: any
